{
	"minecraft:amethyst_block": "magenta;5",
	"minecraft:amethyst_cluster": "magenta;F",
	"minecraft:large_amethyst_bud": "magenta;A",
	"minecraft:medium_amethyst_bud": "magenta;5",
	"minecraft:small_amethyst_bud": "magenta;3",

	"minecraft:brewing_stand": "yellow",
	"minecraft:blast_furnace": {
		"states": {
			"lit=true": "orange;8"
		},
		"default": "#ff4400;1"
	},
	"minecraft:furnace": {
		"states": {
			"lit=true": "orange;7"
		},
		"default": "#ff4400;1"
	},
	"minecraft:smoker": {
		"states": {
			"lit=true": "orange;6"
		},
		"default": "#ff4400;1"
	},

	"minecraft:black_candle": "black",
	"minecraft:blue_candle": "blue",
	"minecraft:brown_candle": "brown",
	"minecraft:candle": "#fff3a7",
	"minecraft:cyan_candle": "cyan",
	"minecraft:gray_candle": "gray",
	"minecraft:green_candle": "green",
	"minecraft:light_blue_candle": "light_blue",
	"minecraft:light_gray_candle": "light_gray",
	"minecraft:lime_candle": "lime",
	"minecraft:magenta_candle": "magenta",
	"minecraft:orange_candle": "orange",
	"minecraft:pink_candle": "pink",
	"minecraft:purple_candle": "purple",
	"minecraft:red_candle": "red",
	"minecraft:white_candle": "white",
	"minecraft:yellow_candle": "yellow",

	"minecraft:brain_coral": "pink;8",
	"minecraft:brain_coral_block": "pink;A",
	"minecraft:brain_coral_fan": "pink;6",
	"minecraft:brain_coral_wall_fan": "pink;6",
	"minecraft:bubble_coral": "magenta;8",
	"minecraft:bubble_coral_block": "magenta;A",
	"minecraft:bubble_coral_fan": "magenta;6",
	"minecraft:bubble_coral_wall_fan": "magenta;6",
	"minecraft:fire_coral": "red;8",
	"minecraft:fire_coral_block": "red;A",
	"minecraft:fire_coral_fan": "red;6",
	"minecraft:fire_coral_wall_fan": "red;6",
	"minecraft:horn_coral": "yellow;8",
	"minecraft:horn_coral_block": "yellow;A",
	"minecraft:horn_coral_fan": "yellow;6",
	"minecraft:horn_coral_wall_fan": "yellow;6",
	"minecraft:tube_coral": "blue;8",
	"minecraft:tube_coral_block": "blue;A",
	"minecraft:tube_coral_fan": "blue;6",
	"minecraft:tube_coral_wall_fan": "blue;6",

	"minecraft:beacon": {
		"default": "white",
		"variants": [
			{ "nbt": "{Primary:1}", "color": "#33ebff" },
			{ "nbt": "{Primary:3}", "color": "#d9c043" },
			{ "nbt": "{Primary:5}", "color": "#ffc700" },
			{ "nbt": "{Primary:8}", "color": "#fdff84" },
			{ "nbt": "{Primary:10}", "color": "#cd5cab" },
			{ "nbt": "{Primary:11}", "color": "#9146f0" }
		]
	},
	"minecraft:conduit": "#9cffff",
	"minecraft:dragon_egg": "magenta;6",
	"minecraft:enchanting_table": "purple",
	"minecraft:ender_chest": "purple",
	"minecraft:glowstone": "yellow",
	"minecraft:jack_o_lantern": "#fff3a7",
	"minecraft:magma_block": "orange;8",
	"minecraft:sea_lantern": "#e0f7f7",
	"minecraft:shroomlight": "#ffc080",

	"minecraft:end_portal": "white;0",
	"minecraft:end_gateway": "white;0",
	"minecraft:end_portal_frame": "white",
	"minecraft:nether_portal": "#d080ff",

	"minecraft:ochre_froglight": "#fff1bf",
	"minecraft:pearlescent_froglight": "#ffbff9",
	"minecraft:verdant_froglight": "#dbffbf",

	"minecraft:azalea": "green;5",
	"minecraft:big_dripleaf": {
		"states": {
			"tilt=none": "green;7",
			"tilt=unstable": "green;7",
			"tilt=partial": "green;6",
			"tilt=full": "green;5"
		},
		"default": "green;7"
	},
	"minecraft:brown_mushroom": "brown",
	"minecraft:cave_vines": "#bfff00",
	"minecraft:cave_vines_plant": "green;7",
	"minecraft:chorus_flower": "pink;12",
	"minecraft:chorus_plant": "purple;6",
	"minecraft:crimson_nylium": "red;A",
	"minecraft:flowering_azalea": "magenta;5",
	"minecraft:glow_lichen": "#b1ebfc;6",
	"minecraft:pitcher_plant": "cyan;6",
	"minecraft:red_mushroom": "red",
	"minecraft:sea_pickle": {
		"states": {
			"pickles=4": "#abccb4;F",
			"pickles=3": "#abccb4;B",
			"pickles=2": "#abccb4;9",
			"pickles=1": "#abccb4;6"
		},
		"default": "white;0"
	},
	"minecraft:small_dripleaf": "green;5",
	"minecraft:spore_blossom": "magenta;5",
	"minecraft:torchflower": "orange;12",
	"minecraft:twisting_vines_plant": "cyan;F",
	"minecraft:warped_fungus": "cyan;A",
	"minecraft:warped_nylium": "cyan;A",
	"minecraft:weeping_vines_plant": "red;F",

	"minecraft:activator_rail": {
		"states": {
			"powered=false": "red;0",
			"powered=true": "red;7"
		},
		"default": "red;0"
	},
	"minecraft:comparator": {
		"states": {
			"powered=false": "red;0",
			"powered=true": "red;7"
		},
		"default": "red;0"
	},
	"minecraft:deepslate_redstone_ore": "red",
	"minecraft:powered_rail": {
		"states": {
			"powered=false": "red;0",
			"powered=true": "red;7"
		},
		"default": "red;0"
	},
	"minecraft:redstone_block": "red;8",
	"minecraft:redstone_lamp": "vanilla",
	"minecraft:redstone_ore": "red",
	"minecraft:redstone_torch": "red",
	"minecraft:redstone_wall_torch": "red",
	"minecraft:redstone_wire": {
		"states": {
			"power=15": "red;7",
			"power=14": "red;7",
			"power=13": "red;6",
			"power=12": "red;6",
			"power=11": "red;5",
			"power=10": "red;5",
			"power=9": "red;4",
			"power=8": "red;4",
			"power=7": "red;3",
			"power=6": "red;3",
			"power=5": "red;2",
			"power=4": "red;2",
			"power=3": "red;1",
			"power=2": "red;1",
			"power=1": "red;0"
		},
		"default": "red;0"
	},
	"minecraft:repeater": {
		"states": {
			"powered=false": "red;0",
			"powered=true": "red;7"
		},
		"default": "red;0"
	},

	"minecraft:calibrated_sculk_sensor": {
		"states": {
			"sculk_sensor_phase=active": "#300044;F",
			"sculk_sensor_phase=cooldown": "#6f0088;5",
			"sculk_sensor_phase=inactive": "#3d0044;A"
		},
		"default": "#3d0044;A"
	},
	"minecraft:sculk": "#0088AA;9",
	"minecraft:sculk_catalyst": "#61c3cb",
	"minecraft:sculk_sensor": {
		"states": {
			"sculk_sensor_phase=active": "#003344;F",
			"sculk_sensor_phase=cooldown": "#006688;5",
			"sculk_sensor_phase=inactive": "#002244;A"
		},
		"default": "#002244;A"
	},
	"minecraft:sculk_vein": "#0088AA;7",

	"minecraft:campfire": {
		"states": {
			"lit=true,signal=false": "#ffac4d",
			"lit=true,signal=true": "#ff8800",
			"lit=false": "#ff4400;1"
		},
		"default": "#ffac4d"
	},
	"minecraft:end_rod": "white",
	"minecraft:fire": "#ff894d",
	"minecraft:lantern": "#fff3a7",
	"minecraft:lava": "#ff5900",
	"minecraft:lava_cauldron": "#ff5900",
	"minecraft:respawn_anchor": {
		"states": {
			"charges=4": "purple;F",
			"charges=3": "purple;B",
			"charges=2": "purple;9",
			"charges=1": "purple;7",
			"charges=0": "#440044;1"
		},
		"default": "purple;0"
	},
	"minecraft:soul_campfire": {
		"states": {
			"lit=true": "#e6feff",
			"lit=false": "#00aaaa;1"
		},
		"default": "#e6feff"
	},
	"minecraft:soul_fire": "#e6feff",
	"minecraft:soul_lantern": "#e6feff",
	"minecraft:soul_torch": "#e6feff",
	"minecraft:soul_wall_torch": "#e6feff",
	"minecraft:torch": "vanilla",
	"minecraft:wall_torch": "vanilla",
	"minecraft:crying_obsidian": "#9800ba"
}